{"_type":"export","__export_format":4,"__export_date":"2020-03-27T17:52:11.860Z","__export_source":"insomnia.desktop.app:v7.1.1","resources":[{"_id":"req_8985f67e1fa54eb48aa85a95b1b72e94","authentication":{},"body":{"mimeType":"application/json","text":"{\n\t\"id\": \"84450e37\"\n}"},"created":1585151692518,"description":"","headers":[{"id":"pair_3e371b981c94470ba2d812caf5194868","name":"Content-Type","value":"application/json"}],"isPrivate":false,"metaSortKey":-1585151692518,"method":"POST","modified":1585151809300,"name":"Create","parameters":[],"parentId":"fld_b304f43fcb8f4326a4c0eb58278bab48","settingDisableRenderRequestBody":false,"settingEncodeUrl":true,"settingFollowRedirects":"global","settingRebuildPath":true,"settingSendCookies":true,"settingStoreCookies":true,"url":"{{ url  }}/session","_type":"request"},{"_id":"fld_b304f43fcb8f4326a4c0eb58278bab48","created":1585151778610,"description":"","environment":{},"environmentPropertyOrder":null,"metaSortKey":-1585151778610,"modified":1585151778610,"name":"Session","parentId":"wrk_6c404cfa92464a7084bf1ab77e8831a8","_type":"request_group"},{"_id":"wrk_6c404cfa92464a7084bf1ab77e8831a8","created":1585054883201,"description":"","modified":1585054883201,"name":"Semana Omnistack 11","parentId":null,"_type":"workspace"},{"_id":"req_548478c999cd477ea39367fc7630a08c","authentication":{},"body":{},"created":1585149241401,"description":"","headers":[{"description":"","id":"pair_abc9cf2db9b04a43b74b919b6fbf3301","name":"authorization","value":"84450e37"}],"isPrivate":false,"metaSortKey":-1585149241401,"method":"DELETE","modified":1585331375604,"name":"Delete","parameters":[],"parentId":"fld_fc2db2bc4d434d4298347b1deb8d152f","settingDisableRenderRequestBody":false,"settingEncodeUrl":true,"settingFollowRedirects":"global","settingRebuildPath":true,"settingSendCookies":true,"settingStoreCookies":true,"url":"{{ url  }}/incident/25","_type":"request"},{"_id":"fld_fc2db2bc4d434d4298347b1deb8d152f","created":1585147676209,"description":"","environment":{},"environmentPropertyOrder":null,"metaSortKey":-1585147676209,"modified":1585147676209,"name":"Incidents","parentId":"wrk_6c404cfa92464a7084bf1ab77e8831a8","_type":"request_group"},{"_id":"req_8b1d1bdb20b644058ae48a1805edf2e5","authentication":{},"body":{},"created":1585148514302,"description":"","headers":[],"isPrivate":false,"metaSortKey":-1585148514302,"method":"GET","modified":1585320991226,"name":"List","parameters":[],"parentId":"fld_fc2db2bc4d434d4298347b1deb8d152f","settingDisableRenderRequestBody":false,"settingEncodeUrl":true,"settingFollowRedirects":"global","settingRebuildPath":true,"settingSendCookies":true,"settingStoreCookies":true,"url":"{{ url  }}/incident?page=3","_type":"request"},{"_id":"req_1c3d54db20a84d94909f1801046dca6b","authentication":{},"body":{"mimeType":"application/json","text":"{\n\t\"title\": \"Caso 1\",\n\t\"description\": \"Detalhes do coso\",\n\t\"value\": 120\n}"},"created":1585147686918,"description":"","headers":[{"id":"pair_adba6ea40ec347e891b1ceed88678520","name":"Content-Type","value":"application/json"},{"description":"","id":"pair_898d387b0d30455ba6418c302b1f0e1e","name":"authorization","value":"84450e37"}],"isPrivate":false,"metaSortKey":-1585147686918,"method":"POST","modified":1585148226036,"name":"Create","parameters":[],"parentId":"fld_fc2db2bc4d434d4298347b1deb8d152f","settingDisableRenderRequestBody":false,"settingEncodeUrl":true,"settingFollowRedirects":"global","settingRebuildPath":true,"settingSendCookies":true,"settingStoreCookies":true,"url":"{{ url  }}/incident","_type":"request"},{"_id":"req_5dcb5b1eb9fd4251b1f8d01c1a59f698","authentication":{},"body":{},"created":1585150953226,"description":"","headers":[],"isPrivate":false,"metaSortKey":-1585150953226,"method":"GET","modified":1585320892128,"name":"Incidents","parameters":[],"parentId":"fld_81967ee022fe40d893f537426bd2df35","settingDisableRenderRequestBody":false,"settingEncodeUrl":true,"settingFollowRedirects":"global","settingRebuildPath":true,"settingSendCookies":true,"settingStoreCookies":true,"url":"{{ url  }}/ongs/84450e37/incidents","_type":"request"},{"_id":"fld_81967ee022fe40d893f537426bd2df35","created":1585062945366,"description":"","environment":{},"environmentPropertyOrder":null,"metaSortKey":-1585062945366,"modified":1585062945366,"name":"Ongs","parentId":"wrk_6c404cfa92464a7084bf1ab77e8831a8","_type":"request_group"},{"_id":"req_f5967cc4cc8f49d9809ef50e36b0c1a2","authentication":{},"body":{},"created":1585147030999,"description":"","headers":[],"isPrivate":false,"metaSortKey":-1585147030999,"method":"GET","modified":1585147037799,"name":"List","parameters":[],"parentId":"fld_81967ee022fe40d893f537426bd2df35","settingDisableRenderRequestBody":false,"settingEncodeUrl":true,"settingFollowRedirects":"global","settingRebuildPath":true,"settingSendCookies":true,"settingStoreCookies":true,"url":"{{ url  }}/ongs","_type":"request"},{"_id":"req_014178f23e334729ac108acba04d6f34","authentication":{},"body":{"mimeType":"application/json","text":"{\n\t\"name\": \"APAD\",\n\t\"email\": \"contato@apad.com.br\",\n\t\"whatsapp\": \"5514900000000\",\n\t\"city\": \"Rio do Sul\",\n\t\"uf\": \"SC\"\n}"},"created":1585062983158,"description":"","headers":[{"id":"pair_a9c3d2c52f3c4464842ae6cc1a4d819b","name":"Content-Type","value":"application/json"}],"isPrivate":false,"metaSortKey":-1585062983158,"method":"POST","modified":1585331329075,"name":"Create","parameters":[],"parentId":"fld_81967ee022fe40d893f537426bd2df35","settingDisableRenderRequestBody":false,"settingEncodeUrl":true,"settingFollowRedirects":"global","settingRebuildPath":true,"settingSendCookies":true,"settingStoreCookies":true,"url":"{{ url  }}/ongs","_type":"request"},{"_id":"env_1fafd461dabc29e3ed746834f09c2a1cd9adc44c","color":null,"created":1585054883282,"data":{"url":"localhost:3333"},"dataPropertyOrder":{"&":["url"]},"isPrivate":false,"metaSortKey":1585054883282,"modified":1585056063737,"name":"Base Environment","parentId":"wrk_6c404cfa92464a7084bf1ab77e8831a8","_type":"environment"},{"_id":"jar_1fafd461dabc29e3ed746834f09c2a1cd9adc44c","cookies":[],"created":1585054883286,"modified":1585054883286,"name":"Default Jar","parentId":"wrk_6c404cfa92464a7084bf1ab77e8831a8","_type":"cookie_jar"}]}